README.rst
setup.cfg
setup.py
reportbro_plus/__init__.py
reportbro_plus/barcode128.py
reportbro_plus/containers.py
reportbro_plus/context.py
reportbro_plus/docelement.py
reportbro_plus/elements.py
reportbro_plus/enums.py
reportbro_plus/errors.py
reportbro_plus/rendering.py
reportbro_plus/reportbro.py
reportbro_plus/structs.py
reportbro_plus/utils.py
reportbro_plus/data/logo_watermark.png
reportbro_plus_lib.egg-info/PKG-INFO
reportbro_plus_lib.egg-info/SOURCES.txt
reportbro_plus_lib.egg-info/dependency_links.txt
reportbro_plus_lib.egg-info/requires.txt
reportbro_plus_lib.egg-info/top_level.txt