Metadata-Version: 1.1
Name: reportbro-plus-lib
Version: 1.5.3
Summary: Generate PDF and Excel reports from visually designed templates
Home-page: UNKNOWN
Author: sdet25
Author-email: andriy.general.nikiforov@gmail.com
License: AGPL-3.0
Keywords: pdf excel report generate create web template layout
Platform: UNKNOWN
Classifier: Development Status :: 5 - Production/Stable
Classifier: Intended Audience :: Developers
Classifier: Topic :: Software Development :: Libraries :: Python Modules
Classifier: License :: OSI Approved :: GNU Affero General Public License v3
Classifier: Programming Language :: Python :: 2
Classifier: Programming Language :: Python :: 2.7
Classifier: Programming Language :: Python :: 3
Classifier: Programming Language :: Python :: 3.5
Classifier: Programming Language :: Python :: 3.6
